{
  "judgment_id": "IN-HC-HIG-2024-CR-0BA701",
  "text": "Madhya Pradesh High Court\n\nAnkit Seharia vs The State Of Madhya Pradesh on 13 August, 2024\n\nAuthor:\nSanjeev S Kalgaonkar\n\nBench:\nSanjeev S Kalgaonkar\n\n1 MCRC-29540-2024\nIN THE HIGH COURT OF MADHYA PRADESH\nAT GWALIOR\nBEFORE\nHON'BLE SHRI JUSTICE SANJEEV S KALGAONKAR\nON THE 13th OF AUGUST, 2024\nMISC. CRIMINAL CASE No. 29540 of 2024\nANKIT SEHARIA\nVersus\nTHE STATE OF MADHYA PRADESH\nAppearance:\nShri Rishikesh Bohare- Advocate for applicant.\n\nShri Dinesh Savita- Public Prosecutor for respondent- State.\n\nORDER\n\nThis first application has been filed by applicant under\nSection 438\nof\nCode of Criminal Procedure for grant of anticipatory bail, who is\napprehending his arrest in connection with Crime No.425 of 2024 registered\nat PS Cantt. District Guna for offence punishable under\nSections 354\n,\n,\nof IPC and added\nSections 376\n,\nof IPC.\n\nAs per the case of prosecution, victim, aged around 25 years, reported\nto PS Guna that on 24-04-2024, she was sleeping at home. Around 12:00 in\n\nthe night, she heard some noise. Her neighbour Ankit Seharia (applicant)\nentered her house by removing iron-sheet from the roof. Ankit caught hold\nof her, pressed her and bite her. She sustained injury on cheek and breast.\nHearing her shouts, her neighbours Puspa and Batobai came to her house.\nThereafter, Ankit fled away. On such allegations, PS Guna registered FIR at\nCrime No.425 of 2024 for offence punishable under\nSections 354\n,\n,\nSignature Not Verified\n\nSigned by: MAHENDRA\n\nBARIK\n\nSigning time: 14-08-2024\n\n10:22:49 PM\n\n2 MCRC-29540-2024\nof\nIPC\nagainst Ankit (applicant). Victim was forwarded for medico-legal\nexamination. One contusion with abraded margin was found on her left\ncheek. Ankit was arrested on 24-04-2024. Statements of witnesses were\nrecorded. Statement of victim was also recorded under\nSection 164\nof CrPC,\nwherein she made same allegation. Applicant was extended the benefit of\nbail vide order dated 13-05-2024. Thereafter, supplementary statement of\nvictim was recorded on 15-05-2024, wherein she alleged that Ankit has\ncommitted rape on her. Earlier, she could not state due to fear of social\ndisrepute. Prosecution for offence punishable under\nSections 376\nand\nof\nIPC was added. Applicant is apprehending arrest in the matter. His\napplication for anticipatory bail under\nSection 438\nof CrPC stands rejected\nvide order dated 01-07-2024 passed by learned Sessions Judge, Guna.\n\nLearned Counsel for the applicant, in addition to the grounds\nmentioned in the application, submitted that applicant has been falsely\nimplicated in this matter. No offence, as alleged is committed by the\napplicant. The allegations of rape are levelled against the applicant after he\nwas extended the benefit of bail. Delay in levelling the allegation\nsubstantiates the defence of the applicant that false allegations are levelled\nagainst him after pre-meditation and consultation. No further custodial\ninterrogation of applicant is needed in the matter. He is ready to cooperate in\nthe investigation. Learned Counsel further submits that applicant is aged\naround 21 years. He is labourer by profession. He has not misused the liberty\nextended vide earlier bail order. No criminal antecedent is reported against\nhim. Therefore, applicant may be extended benefit of anticipatory bail.\n\nSignature Not Verified\n\nSigned by: MAHENDRA\n\nBARIK\n\nSigning time: 14-08-2024\n\n10:22:49 PM\n\n3 MCRC-29540-2024\nPer contra, learned Counsel for the State opposes the anticipatory bail\napplication on the ground of gravity of alleged offence and prays for its\nrejection.\n\nHeard learned counsel for the parties and perused the case diary.\n\nConsidering the arguments advanced by both the parties and overall\ncircumstances of the case, but without commencing on merits of the case,\nthis Court is inclined to grant anticipatory bail to the applicant. Thus, the\napplication is allowed.\n\nAccordingly, it is directed that in the event of arrest of applicant,\napplicant- Ankit Seharia shall be released on bail in relation to Crime No. 425\nof 2024 registered at PS Cantt. District Guna for offence punishable under\n\nSections 354\n,\n,\nof IPC and added\nSections 376\n,\nof IPC, upon\nfurnishing a personal bond in the sum of Rs.50,000/-(Rupees fifty thousand only)\nwith one solvent surety of the same amount to the satisfaction of the Officer\n\nmaking arrest, for compliance with the following conditions: (For convenience\n\nof understanding by accused and surety, the conditions of bail are also\nreproduced in Hindi as under):-\n\n(1) Applicant shall make himself available for investigation as may be directed by\nthe officer, in-charge of investigation;\n\n(1) vUos\"k.kdrkZ iqfyl vf/kdkjh ds funsZ'kkuqlkj vUos\"k.k gsrq vkosnd miyC/k jgsxhA\n(2) Applicant shall not commit or get involved in any offence of similar\nnature;\n\n(2) vkosnd leku izd`fr dk dksbZ vijk/k ugha djsxk ;k mlesa lfEefyr ugha gksxhA\n(3) Applicant shall not directly or indirectly make any inducement, threat or\npromise to any person acquainted with the facts of the case so as to dissuade\nthem/him/her from disclosing such facts to the Court or to the police officer;\n(3) vkosnd izdj.k ds rF;ksa ls ifjfpr fdlh O;fDr dks izR;{k ;k vizR;{k :i ls izyksHku]\n\nSignature Not Verified\n\nSigned by: MAHENDRA\n\nBARIK\n\nSigning time: 14-08-2024\n\n10:22:49 PM\n\n4 MCRC-29540-2024\n/kedh ;k opu ugha nsxh] ftlls ,slk O;fDr ,sls rF;ksa dks U;k;ky; ;k iqfyl vf/kdkjh dks\nizdV djus ls fuokfjr gksA\n(4) Applicant shall not directly or indirectly attempt to tamper with the\nevidence or allure, pressurize or threaten the witness;\n(4) vkosnd izR;{k ;k vizR;{k :i ls lk{; ds lkFk NsMNkM djus dk ;k lk{kh ;k lkf{k;ksa dks\ncgykus&Qqlykus] ncko Mkyus ;k /kedkus dk iz;kl ugha djsxhA\n(5) Upon submission of final report under\nSection 173\nof Cr.P.C/193 of\nBNSS, the applicant shall furnish fresh personal bond and solvent surety of\naforementioned amount to the satisfaction of the Trial Court, if so directed\nand thereafter, shall remain present on every date of hearing as may be\ndirected by the concerned Court;\n\n(5) /kkjk 173 na-iz-la-@193 Hkkjrh; ukxfjd lqj{kk lafgrk ds rgr vafre izfrosnu izLrqr gksus\nij] ;fn ,slk funsZf'kr fd;k tkrk gSZ] vkosnd fopkj.k U;k;ky; dh larqf\"Vizn iwoZ mYysf[kr\njkf'k dk uohu oS;fDrd ca/ki= ,oa izfrHkw ca/ki= izLrqr djsxh vkSj mlds mijkar lacaf/kr\nU;k;ky; ds funsZ'kkuqlkj lquokbZ dh izR;sd frfFk ij mifLFkr jgsxhA\n(6) During trial, the applicant shall ensure due compliance of provisions of\n\nSection 309\nof Cr.P.C/346 of the BNSS. regarding examination of witnesses\nin attendance;\n\n(6) fopkj.k ds nkSjku] mifLFkr xokgksa ls ijh{k.k ds laca/k esa vkosnd /kkjk 309 na-iz-la-@ 346\nHkkjrh; ukxfjd lqj{kk lafgrk ds izko/kkuksa dk mfpr vuqikyu lqfuf'pr djsxhA\n\nThis order shall be effective till the end of trial. However, in case of breach of\n\nany of the precondition of bail, the Trial Court may consider on merit\ncancellation of bail without any impediment of this order.\n\nThe trial Court shall get these conditions reproduced on the personal bond\nby the accused and on surety bond by the surety concerned. If any of them is\nunable to write, the scribe shall certify that he had explained the conditions to the\nconcerned accused or the surety.\n\nC.C. as per rules.\n\n(SANJEEV S KALGAONKAR)\nJUDGE\n\nMKB\n\nSignature Not Verified\n\nSigned by: MAHENDRA\n\nBARIK\n\nSigning time: 14-08-2024\n\n10:22:49 PM\n\n5 MCRC-29540-2024\n\nSignature Not Verified\n\nSigned by: MAHENDRA\n\nBARIK\n\nSigning time: 14-08-2024\n\n10:22:49 PM",
  "metadata": {
    "processed_date": "2026-01-18T18:40:35.911763",
    "version": "2.0",
    "court": "High Court Of Madhya Pradesh At Gwalior Before Hon",
    "court_level": "HC",
    "case_number": "CRIMINAL CASE NO. 29540",
    "decision_date": "13 AUGUST, 2024",
    "jurisdiction": "India",
    "bench": "SANJEEV S KALGAONKAR  1 MCRC-29540-2024 IN THE HIGH COURT OF MADHYA PRADESH AT GWALIOR BEFORE HON'BLE SHRI JUSTICE SANJEEV S KALGAONKAR ON THE 13TH OF AUGUST, 2024 MISC. CRIMINAL CASE NO. 29540 OF 2024 ANKIT SEHARIA VERSUS THE STATE OF MADHYA PRADESH APPEARANCE: SHRI RISHIKESH BOHARE- ADVOCATE FOR APPLICANT.  SHRI DINESH SAVITA- PUBLIC PROSECUTOR FOR RESPONDENT- STATE.  ORDER  THIS FIRST APPLICATION HAS BEEN FILED BY APPLICANT UNDER SECTION 438 OF CODE OF CRIMINAL PROCEDURE FOR GRANT OF ANTICIPATORY BAIL, WHO IS APPREHENDING HIS ARREST IN CONNECTION WITH CRIME NO.425 OF 2024 REGISTERED AT PS CANTT. DISTRICT GUNA FOR OFFENCE PUNISHABLE UNDER SECTIONS 354 , , OF IPC AND ADDED SECTIONS 376 , OF IPC.  AS PER THE CASE OF PROSECUTION, VICTIM, AGED AROUND 25 YEARS, REPORTED TO PS GUNA THAT ON 24-04-2024, SHE WAS SLEEPING AT HOME. AROUND 12:00 IN  THE NIGHT, SHE HEARD SOME NOISE. HER NEIGHBOUR ANKIT SEHARIA (APPLICANT) ENTERED HER HOUSE BY REMOVING IRON-SHEET FROM THE ROOF. ANKIT CAUGHT HOLD OF HER, PRESSED HER AND BITE HER. SHE SUSTAINED INJURY ON CHEEK AND BREAST. HEARING HER SHOUTS, HER NEIGHBOURS PUSPA AND BATOBAI CAME TO HER HOUSE. THEREAFTER, ANKIT FLED AWAY. ON SUCH ALLEGATIONS, PS GUNA REGISTERED FIR AT CRIME NO.425 OF 2024 FOR OFFENCE PUNISHABLE UNDER SECTIONS 354 , , SIGNATURE NOT VERIFIED  SIGNED BY: MAHENDRA  BARIK  SIGNING TIME: 14-08-2024  10:22:49 PM  2 MCRC-29540-2024 OF IPC AGAINST ANKIT (APPLICANT). VICTIM WAS FORWARDED FOR MEDICO-LEGAL EXAMINATION. ONE CONTUSION WITH ABRADED MARGIN WAS FOUND ON HER LEFT CHEEK. ANKIT WAS ARRESTED ON 24-04-2024. STATEMENTS OF WITNESSES WERE RECORDED. STATEMENT OF VICTIM WAS ALSO RECORDED UNDER SECTION 164 OF CRPC, WHEREIN SHE MADE SAME ALLEGATION. APPLICANT WAS EXTENDED THE BENEFIT OF BAIL VIDE ORDER DATED 13-05-2024. THEREAFTER, SUPPLEMENTARY STATEMENT OF VICTIM WAS RECORDED ON 15-05-2024, WHEREIN SHE ALLEGED THAT ANKIT HAS COMMITTED RAPE ON HER. EARLIER, SHE COULD NOT STATE DUE TO FEAR OF SOCIAL DISREPUTE. PROSECUTION FOR OFFENCE PUNISHABLE UNDER SECTIONS 376 AND OF IPC WAS ADDED. APPLICANT IS APPREHENDING ARREST IN THE MATTER. HIS APPLICATION FOR ANTICIPATORY BAIL UNDER SECTION 438 OF CRPC STANDS REJECTED VIDE ORDER DATED 01-07-2024 PASSED BY LEARNED SESSIONS JUDGE, GUNA.  LEARNED COUNSEL FOR THE APPLICANT, IN ADDITION TO THE GROUNDS MENTIONED IN THE APPLICATION, SUBMITTED THAT APPLICANT HAS BEEN FALSELY IMPLICATED IN THIS MATTER. NO OFFENCE, AS ALLEGED IS COMMITTED BY THE APPLICANT. THE ALLEGATIONS OF RAPE ARE LEVELLED AGAINST THE APPLICANT AFTER HE WAS EXTENDED THE BENEFIT OF BAIL. DELAY IN LEVELLING THE ALLEGATION SUBSTANTIATES THE DEFENCE OF THE APPLICANT THAT FALSE ALLEGATIONS ARE LEVELLED AGAINST HIM AFTER PRE-MEDITATION AND CONSULTATION. NO FURTHER CUSTODIAL INTERROGATION OF APPLICANT IS NEEDED IN THE MATTER. HE IS READY TO COOPERATE IN THE INVESTIGATION. LEARNED COUNSEL FURTHER SUBMITS THAT APPLICANT IS AGED AROUND 21 YEARS. HE IS LABOURER BY PROFESSION. HE HAS NOT MISUSED THE LIBERTY EXTENDED VIDE EARLIER BAIL ORDER. NO CRIMINAL ANTECEDENT IS REPORTED AGAINST HIM. THEREFORE, APPLICANT MAY BE EXTENDED BENEFIT OF ANTICIPATORY BAIL.  SIGNATURE NOT VERIFIED"
  },
  "extractions": {
    "citations": {
      "total": 0,
      "by_type": {},
      "details": []
    },
    "sections": {
      "total": 6,
      "by_act": {
        "IPC": [
          "354",
          "376"
        ],
        "CrPC": [
          "164",
          "438",
          "173",
          "309"
        ]
      },
      "details": [
        {
          "section": "354",
          "act": "IPC"
        },
        {
          "section": "376",
          "act": "IPC"
        },
        {
          "section": "164",
          "act": "CrPC"
        },
        {
          "section": "438",
          "act": "CrPC"
        },
        {
          "section": "173",
          "act": "CrPC"
        },
        {
          "section": "309",
          "act": "CrPC"
        }
      ]
    },
    "transitions": {
      "total": 1,
      "by_source": {
        "inferred_from_ipc": 1
      },
      "details": [
        {
          "ipc": "376",
          "bns": "64",
          "source": "inferred_from_ipc",
          "validated": false,
          "risk": "high",
          "confidence": "low",
          "requires_judicial_confirmation": true,
          "note": "Inferred from standalone IPC 376 mention. Not validated by judgment text."
        }
      ]
    },
    "landmarks": {
      "total": 0,
      "by_id": {},
      "details": []
    },
    "issues": {
      "total": 1,
      "details": {
        "bail": {
          "statute": "CrPC / BNSS",
          "keywords": [
            "bail",
            "anticipatory bail"
          ],
          "sections": [
            "438"
          ],
          "confidence": "high",
          "keyword_count": 2,
          "mention_count": 17
        }
      }
    }
  },
  "provenance": {
    "processed_date": "2026-01-18T18:40:35.911763",
    "pipeline_version": "2.0",
    "processing_steps": [
      "ingestion",
      "metadata_extraction",
      "issue_extraction",
      "classification",
      "statutory_transitions",
      "citation_extraction",
      "consolidation"
    ]
  },
  "classification": {
    "domain": "criminal",
    "confidence": "high",
    "signals": {
      "criminal": [
        "accused",
        "offence",
        "fir",
        "Code of Criminal Procedure",
        "bail",
        "BNSS",
        "IPC",
        "CrPC"
      ],
      "civil": [],
      "service": []
    }
  }
}