{
  "judgment_id": "IN-SC-SUP-2018-CV-CC7AE5",
  "text": "Supreme Court of India\n\nP.Radha Bai vs P.Ashok Kumar on 26 September, 2018\n\nEquivalent citations: AIR 2018 SUPREME COURT 5013, 2019 (13) SCC 445, (2018) 191 ALLINDCAS 36 (SC), (2018) 13 SCALE 60, (2018) 191 ALLINDCAS 36, (2018) 2 WLC(SC)CVL 674, (2018) 4 CURCC 247, (2018) 4 RECCIVR 571, (2018) 5 ARBILR 204, (2018) 8 MAD LJ 496, 2019 (134) ALR SOC 31 (SC), (2019) 1 ANDHLD 38, (2019) 1 CIVLJ 836, AIR 2019 SC (CIV) 609, AIRONLINE 2018 SC 255\n\nAuthor:\nN.V. Ramana\n\nBench:\nS. Abdul Nazeer\n,\nN. V. Ramana\n\nReportable\n\nIN THE SUPREME COURT OF INDIA\nCIVIL APPELLATE JURISDICTION\n\nCIVIL APPEAL NO(S). 7710­7713 OF 2013\n\nP. RADHA BAI AND ORS. …APPELLANT(S)\n\nVERSUS\nP. ASHOK KUMAR AND ANR.               …RESPONDENT(S)\n\nJ U D G M E N T\nN.V. RAMANA, J.\n\n1. These   appeals   are   filed,   aggrieved   by   the   judgment   and\n\norder dated  18.06.2012 in the Civil Revision Petition Nos.\n\n2151,   2246,   2383   and   2458   of   2012   passed   by   the   High\n\nCourt of Judicature at Andhra Pradesh at Hyderabad.\n\n2. An   interesting   question   of   law   arises   in   this   batch   of\n\npetitions, concerning the applicability of\nSection 17\nof the\n\nLimitation Act, 1963 [‘\nLimitation Act\n’] for condonation of a\n\ndelay caused on the account of alleged fraud played on the\n\nSignature Not Verified\n\nDigitally signed by\n\nVISHAL ANAND\n\nDate: 2018.09.26\n\n14:57:29 IST\n\nobjector   (party   challenging   the   award)   beyond   the   period\n\nReason:\nprescribed   under\nSection   34   (3)\nof   the   Arbitration   and\n\nConciliation Act of 1996 [‘\nArbitration Act\n’].\n\n3. The facts which give rise to this question fall into a narrow\n\ncompass.   Originally   one   Mr.   P.   Kishan   Lal   carried   on\n\nbusiness   and   acquired   several   properties.     On   his   death,\n\nMr.   P.   Kishan   Lal   was   survived   by   eight   (8)   legal   heirs\n\n(Appellant Nos. 1 to 6 and Respondent Nos. 1 and 2).\n\n4. After   the   death   of   Mr.   Kishan   Lal,   several   disputes   have\n\ncropped up on the division of properties.   Having failed to\n\nresolve the dispute, the parties turned towards arbitration\n\nto resolve the dispute.   Five Arbitrators were appointed to\n\nadjudicate   and   distribute   eleven   properties   belonging   to\n\nthem.\n\n5. On 18.02.2010, the arbitrators passed a unanimous Award\n\nproviding for the division of properties and businesses. The\n\nparties   received   the   Award   on   21.02.2010.     There   is   no\n\ndispute on the receipt of the Award by the parties.\n\n6. The Respondents allege that after the pronouncement of the\n\naward,   the   Appellants   in   bad   faith   entered   into   a\n\nMemorandum   of   Understanding   (MoU)   with   the\nRespondents. According to the Respondents, the Appellants\n\nagreed   to  give   certain  additional  properties to  Respondent\n\nNo.   1,   which   were   more   than   what   were   provided   in   the\n\nAward. The Respondents alleged that after entering into the\n\nMoU,   the   Appellants   were   required   to   execute   Gift   and\n\nRelease   Deeds   to   give   effect   to   the   MoU.   However,   the\n\nAppellants   delayed   the   execution   of   the   Gift   and   Release\n\nDeeds as contemplated by the MoU.\n\n7. In the meanwhile, the three­month period and the extended\n\nperiod of 30 days for challenging an Award under\nSection\n\n34(3)\nof the Arbitration Act had expired. After the time limit\n\nexpired, the Appellants filed an Execution Petition (EP) for\n\nexecution of the Award.   The trial court held that EP was\n\nnot maintainable. On appeal, the High Court set aside the\n\norder of the trial court and held that the Execution Petition\n\nwas maintainable and directed the trial court to decide it on\n\nmerits.\n\n8. When   the   Respondents   realized   that   the   Appellants   were\n\ndelaying the execution of the Gift Deed contemplated by the\n\nMoU,   the   Respondents on 08.02.2011 filed an  application\n\nunder\nSection 34(3)\nof the Arbitration Act for setting aside\nthe  Award.  This filing was 236 days after the receipt of the\n\nAward   by   the   Respondents.     The   application   was\n\naccompanied by another application under\nSection 5\nof the\n\nLimitation Act seeking condonation of the delay of 236 days.\n\nIn the application for condonation of delay, the Respondents\n\nalleged that:\n\na. Award was served on the Respondents on 21.02.2010;\n\nb. They were laypersons and were not aware of the legal\n\nrequirement   of   filing   objections   within   the   period\n\nprescribed under the\nArbitration Act\n.\n\nc. Since they were dissatisfied with the Award, they raised\n\nobjections   before   the   learned   Arbitrators.     The\n\nArbitrators   called   upon   all   the   parties   and   conducted\n\nconciliation.     Accordingly,   the   parties   entered   into   a\n\nMoU.  The MoU contemplated for execution of Gift Deed\n\nand   Release   Deed   in   favour   of   Respondent   No.1.\n\nHowever, the Appellants failed to execute the required\n\ndocuments as per the MoU with an intent to defeat their\n\nrights.\nd. One   of  the  Respondents was physically indisposed for\n\none month.\n\n9. During   the   pendency   of   the   aforesaid   interim   application,\n\nseeking   condonation   of   the   delay,   the   Respondents   filed\n\nanother application being I.A. No. 1977 of 2011 in I.A. No.\n\n598 of 2011, seeking an order of the trial court to summon\n\nthe   Sub­registrar,   Charminar   to   prove   the   veracity   of   the\n\nMemorandum   of   Understanding   and   to   counter   the\n\nallegations   raised   by   the   Appellants   herein,   as   to   the\n\nfalsification   and   fabrication   of   the   Memorandum   dated\n\n09.04.2010. For completeness of narration, it may be stated\n\nthat additional I.A.s, being I.A. No. 210 and 211 of 2012,\n\nwere sought by the Respondent seeking certain documents\n\nto be brought on record.\n\n10. By order dated 21.02.2012, the trial court dismissed the IA.\n\nNo. 598 of 2011, pertaining to the condonation of delay in\n\nfiling   the\nSection   34\napplication.   The   Trial   Court   while\n\ndismissing   the   aforesaid   application   as   indicated   above,\n\nreasoned as under­\ni. That   the   Court   is   not   empowered   to   stretch   the\n\nlimitation period beyond the requisite period given\n\nunder\nSection 34\nof the Arbitration Act.\nii. Placing   reliance   on\nUnion   of   India   vs.  Popular\n\nConstruction   Co.\n,   (\n2001)   8   SCC   470   and\n\nConsolidated   Engineering   Enterprises   vs.\n\nPrincipal   Secretary,   Irrigation   Department\n,\n\n(2008) 7 SCC 169, held that the language of\nSection\nof   the   Arbitration   Act   mandated   a   strict\n\nadherence   to   the   time   period   provided   thereunder\n\nand   the   extension   beyond   the   same   was   not\n\npossible   under   any   circumstances.   Therefore,\n\nSection 5\nof the Limitation Act was not applicable to\n\nan   application   filed   under\nSection   34\nof   the\n\nArbitration Act.\n\niii. Based   on   the   aforesaid   judgments   of   this   Hon’ble\n\nCourt,   and   the provisions  of\nSection  34 (3)\nof  the\n\nArbitration   Act,   the   City   Civil   Court   held   that\n\nSection   5\nof   the   Limitation   Act,   1963,   has   no\n\napplication, as the Court has no power to condone\n\nthe delay beyond three months and thirty days. On\nthis ground alone, the objections filed under\nSection\nwere liable to be dismissed.\n\niv. That the trial court rejected the contention that the\n\nRespondent   (objector)   was   unable   to   file   the\n\nobjections   within   the   period   of   limitation   on   the\n\nground   of   illness   and   no   medical   certificate   was\n\nprovided to substantiate such claim.\n\nv. That ignorance of law on behalf of the Respondents,\n\nto be not aware of the technicalities provided under\n\nSection 34\nof the Arbitration Act was not excusable.\nvi. Moreover, the trial court came to a conclusion that\n\nequitable   grounds   cannot   be   utilized   to   create\n\nexceptions not mandated under the statutory law.\n\nWe may note that the trial court although discussed about\n\nthe existence of the Memorandum of Understanding dated\n\n09.04.2010   and   its   impact   on   the   Respondent’s   delay   in\n\nfiling   the\nSection   34\napplication,   there   is   no   specific\n\ndiscussion concerning the applicability of\nSection 17\nof the\n\nLimitation   Act   in   the   trial   court   order.   Moreover,   other\n\ninterim   applications   filed   by   the   respondents   were   also\n\ndismissed consequentially.\n11. Being   aggrieved   by   the   dismissal,   respondents   preferred\n\nfour   Civil   Revision   petitions,   before   the   High   Court   of\n\nAndhra   Pradesh   under\nArticle   227\nof   the   Constitution   of\n\nIndia, being C.R.P. No. 2151, 2246, 2383 and 2458 of 2012.\n\nBy the  impugned order dated 18.06.2012, the High Court\n\nremanded   the   matter   to   the   trial   court   concerning   the\n\napplicability   of\nSection   17\nof   the   Limitation   Act   in   an\n\napplication   under\nSection   34\nof   the   Arbitration   Act.   The\n\nHigh Court observed\n\n“Even though Mr. K. Prabhakar, learned counsel\nfor the respondents sought to argue that when\n\nSection  5\nof   the Act  is excluded,  automatically\n\nSection 17\nof the Act also gets excluded, I refrain\nfrom   expressing   any   opinion   on   this   aspect,\nbecause this is required to be considered by the\nlower court at the first instance before this Court\nexamines the same at an appropriate stage. On\nthis   short   ground,  I   feel   that   it   is   just   and\nappropriate to remand the matter back to the\nlearned   Chief   Judge,   City   Civil   Court,\nHyderabad   for   considering   the   above­\nmentioned   pleadings   of   the   petitioners   and\npronouncing upon the same with reference to\nthe applicability or otherwise of the provision\nof\nSection   17\nof   the   Act.  Therefore,   without\nexpressing   any   opinion   on   these   aspects,   the\nlearned Chief Judge is directed to reconsider the\ncase only to this limited extent and pass a fresh\norder after hearing both parties, within a period\nof   two   months   from   the   date   of   receipt   of   this\norder.   It   is   made   clear   that   the   orders   of   the\nlower Court in respect of the other aspects stand\nconfirmed”.\n\n(emphasis supplied)\n\n12. Aggrieved by the remand order passed by the High Court on\n\nthe applicability of\nSection 17\nof the Limitation Act to the\n\nproceedings, the Appellants have approached this Court in\n\nthese appeals.\n\n13. Before we delve into any other aspect of this case, it may be\n\nimportant to note that we would have agreed with the High\n\nCourt wherein a remand may have been required in usual\n\ncourse for considering the applicability of\nSection 17\nof the\n\nLimitation   Act   as   there   is   an   apparent   insufficiency   of\n\nreasons in the trial court order. But, in this case there has\n\nbeen a considerable delay in resolving the dispute. The very\n\npurpose   of   speedy   justice   delivery   mechanism   would   be\n\nfrustrated by such delays if the matter is allowed to linger\n\nbefore the courts. We had positively persuaded the parties\n\nseveral times to come to an amicable settlement and asked\n\nthe advocates representing them to use their good offices to\n\nrefer   parties   to   mediation   and   avoid   decades   of   litigation.\nBut,   our   efforts   were   not   met   with   much   success   in   any\n\nevent.\n\n14. The   High   Court   could   have   examined   the   legal   issue   of\n\napplicability   of\nSection   17\nof   the   Limitation   Act   to   an\n\napplication   filed   under\nSection   34\nof   the   Arbitration   Act.\n\nThis   is   a   pure   question   of   law.   Only   if\nSection   17\nof\n\nLimitation  Act  was   applicable to a Section 34 application,\n\nthe   question   of   factual   satisfaction   of   the   ingredients   of\n\nSection 17\nto the present case and a consequent remand to\n\nthe trial court would arise.\n\n15. The   learned   counsel   for   the   appellants,   Mr.   Devansh   A.\n\nMohta, argued that­\ni. Limitation period provided under\nSection 34 (3)\nof the\n\nArbitration   Act   begins   ‘only’   upon   the   receipt   of   the\n\naward by the parties and the same cannot be diluted\n\nby   a   different   starting   point   provided   under   the\n\nLimitation   Act\n,   in   light   of\nSection   29   (2)\nof   the\n\nLimitation Act.\nii. The   period   of   limitation   under\nSection   34(3)\nof   the\n\nArbitration   Act   is   ‘unbreakable’  and   is  meant  to   run\n\ncontinuously.\n\niii. Definitive time limit is necessary to ensure expeditious\n\nand   effective   resolution   of   disputes   between   the\n\nparties.\n\niv. The   mandate   of  Popular   Construction   Case  (supra)\n\nand  Consolidated Engineering Case (supra) wherein\n\nthe emphasis on ‘fixed period’ needs to be given effect\n\nto.\n\nv. The expression ‘had received the arbitral award’ found\n\nin\nSection   34   (3)\nof   the   Arbitration   Act   expressly\n\nexcludes   applicability   of\nSection   17\nof   the  Limitation\n\nAct.\n\nvi. This   Court   should   appreciate   the   difference   between\n\nconcealment   of   right   to   action   being   different   from\n\npreventing a person from taking action.\n\n16. On the contrary, the learned counsel for the respondents,\n\nMr. Yashraj Singh Deora, had contended that­\n\ni. The reasoning provided under\nPopular Construction\n\nCase  (\nsupra)   and  Consolidated   Engineering\nCase\n\n(supra) clearly indicates to the applicability of\nSection\nof the Limitation Act, similar to the applicability of\n\nSection 14\nof the Limitation Act.\n\nii.\nLimitation   Act\nis   applicable   to   all   proceedings   before\n\nthe court.\n\niii. It is evident that the\nArbitration Act\nunder Section 34\n\n(3)   provides   for   a   different   time   period   than   the   one\n\npresent   under\nArticle   137\nof   the\nLimitation   Act\n,\n\naccordingly, the special law would therefore, prevail in\n\nso far as the issue of period of limitation is concerned.\n\nHowever, for ‘computation of the period of limitation’ or\n\narriving   at   the   ‘prescribed   period’   the   provisions   of\n\nSection   4\nto\nof   the   Limitation   Act   would\n\nautomatically apply unless they are expressly excluded\n\nby the special law.\n\niv. That   it   has   been   highly   inequitable   for   the\n\nrespondents, who were victims of bad faith negotiation\n\nundertaken   by   the   Appellants   to   derail   the\n\nrespondents from pursuing this case for enforcement\n\nof their rights.\n\n17. We have heard the counsels for both the parties at length,\n\nand also perused the material available on record.\n18. We are now to examine whether\nSection 17\nof the Limitation\n\nAct   is   applicable   while   determining   the   limitation   period\n\nunder\nSection 34(3)\nof the Arbitration Act?\n\n19. This analysis has to necessarily begin from\nSection 29(2)\nof\n\nthe Limitation Act, which  states\n\n29 (2)  Where any special or local law prescribes\nfor   any   suit,   appeal   or   application   a   period   of\nlimitation different from the period prescribed by\nthe   Schedule,   the   provisions   of\nSection   3\nshall\napply   as   if   such   period   were   the   period\nprescribed by the Schedule  and  for the purpose\nof determining any period of limitation prescribed\nfor any suit, appeal or application by any special\nor local law, the provisions contained in\nSections\nto\n24 (inclusive)\nshall apply only in so far as,\nand to the extent to which, they are not expressly\nexcluded by such special or local law.\n\n(emphasis added)\n\n20.\nSection 29(2)\nis divided into 2 limbs. This is evident from the\n\nconjunctive   “and”   in   the   said   provision.   The   inter­relation\n\nbetween these two limbs was considered by a Bench of five\n\nJudges   of   this   Court   in\nVidyacharan   Shukla   v.\n\nKhubchand Baghel\n, [1964] 6 SCR 129.\n\n21. The first part stipulates that the limitation period prescribed\n\nby the special law or local law will prevail over the limitation\n\nperiod prescribed in the\nSchedule to the Limitation Act\n. In\nthis   case,   the\nArbitration   Act\nis   a   “special   law”   which\n\nprescribes a specific period of limitation in Section 34(3) for\n\nfiling objections to an arbitral award passed under the 1996\n\nAct   and   consequently   the   provisions   of\nArbitration   Act\n\nwould apply. We also note that there is no provision under\n\nthe\nLimitation Act\ndealing with challenging an Award passed\n\nunder the\nArbitration Act\n.\n\n22. The   second   part   mandates   that\nSections   4\nto\nof   the\n\nLimitation   Act   will   apply   for   determining   the   period   of\n\nlimitation “only in so far as, and to the extent to which, they\n\nare   not   expressly   excluded   by   such   special   or   local   law.”\n\nThus   the   extent   of   the   application   of\nSections   4\nto\nof\n\nLimitation   Act   will   apply   for   determining   the   limitation\n\nperiod   under   the\nArbitration   Act\nonly   if   they   are   not\n\nexpressly excluded by\nArbitration Act\n.\n\n23. We   are   conscious   that   this     Court   in   several\n\npronouncements has extended\nSection 14\nof Limitation Act\n\nto\nSection  34\nof   Arbitration Act and thereby  excluded the\n\ntime   spent   in   bonafide   pursuing   proceedings   in   a   Court\n\nwhich   lacks   jurisdiction.   (\nState   of   Goa   v.   Western\nBuilders\n(2006)   6   SCC   239   at   para   25;\nConsolidated\n\nEngineering   Enterprises   v.   Principal   Secretary,\n\nIrrigation   Department\n,  (2008)   7   SCC   169     at   para   27\n\nand   29;\nCoal   India   Ltd.   v.   Ujjal   Transport   Agency\n,\n\n(2011)   1   SCC   117   at   para   6;\nM.P.   Housing   Board   v.\n\nMohanlal   &   Co.\n,   (2016)   14   SCC   199   at   para   13).\n\nSimilarly,   this   Court   also   extended   Section   12   of   the\n\nLimitation Act to the Arbitration Act and excluded  the day\n\non   which   the   Award   was   received   from   computing   the\n\nstarting  period   under Section 34(3). We note that none of\n\nthese cases dealt with the question whether the scheme of\n\nSection 17\nof the Limitation Act is consistent with\nSection\nof the Arbitration Act.\n\n24. Relying   on   these   pronouncements,   the   Respondents’\n\ncounsel   asserted   that   there   is   no   express   exclusion   of\n\nSection 17\nin the\nArbitration Act\nand therefore the benefit of\n\nSection   17\nof   Limitation   Act   should   be   extended   while\n\ndetermining the period of limitation under Section 34(3).\n\n25. This requires us to consider the phrase “express exclusion”\n\nin\nSection 29(2)\nof the Limitation Act. This Court in a series\n\nof   cases   held   that   the   express   exclusion   can   be   inferred\neither   from   the   language   of   the   special   law   or   it   can   be\n\nnecessarily   implied   from   the   scheme   and   object   of   the\n\nspecial law.\n\n26. A   Bench   of   five   Judges   in\nVidyacharan\n\nShukla v. Khubchand   Baghel\n,  AIR   1964   SC   1099,\n\ninterpreting the phrase “express exclusion” observed:\n\n“The   contention   is   that   sub­section   (3)   of\nSection 116­\nA of the Act\nnot only provides a\nperiod of limitation for such an appeal, but\nalso   the   circumstances   under   which   the\ndelay   can   be   excused,   indicating   thereby\nthat the general provisions of the\nLimitation\nAct\nare excluded. There are two answers to\nthis   argument.   Firstly,\nSection   29(2)(a)\nof\nthe   Limitation   Act   speaks   of   express\nexclusion but there is no express exclusion\nin   sub­section   (3)   of   Section   116­\nA   of   the\nAct\n;  secondly,   the   proviso   from   which   an\nimplied   exclusion   is   sought   to   be   drawn\ndoes   not   lead   to   any   such   necessary\nimplication”.\n\n27. This   principle   was   further   crystallised   in\nHukumdev\n\nNarain Yadav v. Lalit Narain Mishra\n, (1974) 2 SCC 133\n\nwherein a Bench of three Judges held that:\n\n\"It   is   contended   before   us   that   the   words\n\"expressly   excluded\"   would   mean   that   there\nmust   be   an   express   reference   made   in   the\nspecial or local law to the specific provisions of\nthe\nLimitation Act\nof which the operation is to\nbe excluded. As usual the meaning given in the\nDictionary has been relied upon, but what we\nhave   to   see   is   whether   the   scheme   of   the\nspecial law, that is, in this case the Act, and\nthe nature of the remedy provided therein are\nsuch   that   the   Legislature   intended   it   to   be   a\ncomplete   code   by   itself   which   alone   should\ngovern the several matters provided by it. If on\nan examination of the relevant provisions it is\nclear that the provisions of the\nLimitation Act\n\nare   necessarily   excluded,   then   the   benefits\nconferred   therein   cannot   be   called   in   aid   to\nsupplement   the   provisions   of   the   Act.  In   our\nview, even in a case where the special taw does\nnot exclude the provisions of\nSections 4\nto\nof the Limitation Act by an express reference, it\nwould   nonetheless   be   open   to   the   Court   to\nexamine   whether   and   to   what   extent   the\nnature of those provisions or the nature of the\nsubject­matter and scheme of the special law\nexclude their operation”. (emphasis added)\n\n28. A Bench of three Judges in\nCommissioner of Customs\n\nand Central Excise v. Hongo India (P) Ltd.\n, (2009) 5\n\nSCC 791 reiterated this principle when it held:\n\n“It   was   contended   before   us   that   the   words\n“expressly   excluded”   would   mean   that   there\nmust   be   an   express   reference   made   in   the\nspecial or local law to the specific provisions\nof the\nLimitation Act\nof which the operation is\nto be excluded. In this regard, we have to see\nthe scheme of the special law which here in\nthis case is the\nCentral Excise Act\n. The nature\nof   the   remedy   provided   therein   is   such   that\nthe   legislature   intended   it   to   be   a   complete\ncode by itself which alone should govern the\nseveral   matters   provided   by   it.   If,   on   an\nexamination   of   the   relevant   provisions,   it   is\nclear that the provisions of the\nLimitation Act\n\nare   necessarily   excluded,   then   the   benefits\nconferred   therein   cannot   be   called   in   aid   to\nsupplement the provisions of the Act. In our\nconsidered view, that even in a case where the\nspecial law does not exclude the provisions of\n\nSections 4\nto\nof the Limitation Act by an\nexpress   reference,   it   would   nonetheless   be\nopen to the court to examine whether and to\nwhat extent, the nature of those provisions or\nthe nature of the subject­matter and scheme\nof the special law exclude their operation.  In\nother words, the applicability of the provisions\nof the\nLimitation Act\n, therefore, is to be judged\nnot from the terms of the\nLimitation Act\nbut\nby   the   provisions   of   the\nCentral   Excise   Act\n\nrelating to filing of reference application to the\nHigh Court”.\n\n29. These principles were reiterated by this Court in\nUnion of\n\nIndia v. Popular Construction Co.\n, (2001) 8 SCC 470 at\n\npage   474;\nChhattisgarh   State   Electricity   Board   v.\n\nCentral   Electricity   Regulatory   Commission\n,   (2010)   5\n\nSCC   23   at   para   32;\nGopal   Sardar   v.   Karuna   Sardar\n,\n\n(2004) 4 SCC 252 at para 13.\n30. Thus, the inquiry is ­ whether the text or the scheme and\n\nobject   of   the\nArbitration   Act\nexcludes   the   application   of\n\nSection 17\nof Limitation Act while determining the limitation\n\nperiod?\n\n31. We therefore have to contrast\nSection 17\nof the Limitation\n\nAct with\nSection 34(3)\nof the Arbitration Act. The relevant\n\npart of\nSection 17\nstates\n\n17. Effect of fraud or mistake.—\n\n(1) Where, in the case of any suit or application\nfor which a period of limitation  is prescribed by\nthis Act,—\n\n(a)   the   suit   or   application   is   based   upon   the\nfraud\nof the defendant or respondent or his agent; or\n\n(b) the knowledge of the right or title on which a\nsuit or application is founded is concealed by the\nfraud of any such person as aforesaid; or\n\n(c)  the   suit  or   application  is for  relief from  the\nconsequences of a mistake; or\n\n(d) where  any  document necessary to establish\nthe   right   of   the  plaintiff   or  applicant   has   been\nfraudulently concealed from him,\n\nthe   period   of   limitation   shall   not   begin   to   run\nuntil   plaintiff   or   applicant   has   discovered   the\nfraud or the mistake or could, with reasonable\ndiligence, have discovered it; or in the case of a\nconcealed   document,   until   the   plaintiff   or   the\napplicant first had the means of producing the\nconcealed   document   or   compelling   its\nproduction:\n\n32.\nSection 17\ndoes not extend or break the limitation period. It\n\nonly   postpones   or   defers   the   commencement   of   the\n\nlimitation period. This is evident from the phrase “the period\n\nof limitation shall not begin to run”.\n\n33. In contrast,\nSection 34(3)\nof the Arbitration Act states\n\n34. Application for setting aside arbitral award­\n…\n…\n(3) An application for setting aside  may not be\nmade after three months have elapsed from the\ndate on which the party making that application\nhad received the arbitral award or, if a request\nhad been made under section 33, from the date\non which that request had been disposed of by\nthe arbitral tribunal.\n\nProvided   that   if   the   Court   is   satisfied   that   the\napplicant was prevented by sufficient cause from\nmaking the application within the said period of\nthree   months   it   may   entertain   the   application\nwithin   a   further   period   of   thirty   days,  but   not\nthereafter. (emphasis added)\n\n34. Section   34(3)   deserves   careful   scrutiny   and   its\n\ncharacteristics must be highlighted:\n(a) Section 34 is the only remedy for challenging an award\n\npassed under\nPart I of the Arbitration Act\n. Section 34(3)\n\nis   a   limitation   provision,   which   is   an   inbuilt   into   the\n\nremedy   provision.   One   does   not   have   to   look   at   the\n\nLimitation Act\nor any other provision for identifying the\n\nlimitation period for challenging an Award passed under\n\nPart I of the Arbitration Act\n.\n\n(b) The time limit for commencement of limitation period is\n\nalso provided in Section 34(3) i.e. the time from which a\n\nparty   making   an  application \"had  received   the  Arbitral\n\nAward”   or   disposal   of   a   request   under   Section   33   for\n\ncorrections and interpretation of the Award.\n\n(c) Section   34(3)   prohibits   the   filing   of   an   application   for\n\nsetting   aside   of   an   Award   after   three   months   have\n\nelapsed from the date of receipt of Award or disposal of a\n\nrequest under Section 33. Section 34(3) uses the phrase\n\n“an application for setting aside may not be made after\n\nthree   months   have   elapsed”.     The   phrase   “may   not   be\n\nmade” is from the UNCITRAL Model Law1  and has been\n\n1 “ An application for setting aside may not be made after three months have\nelapsed   from   the   date   on   which   the   party   making   that   application   had\nreceived the award or, if a request had been made under\narticle 33\n, from the\ndate on which that request had been disposed of by the arbitral tribunal”.\nunderstood to mean “cannot be made”. The High Court\n\nof Singapore in ABC Co. Ltd v. XYZ Co. Ltd, [2003] SGHC\n\n107)\n“The starting point of this discussion must be\nthe Model Law itself.   On the aspect of time,\n\nArticle   34(3)\nis   brief.     All   it   says   is   that   the\napplication may not be made after the lapse of\nthree months from a specified date.   Although\nthe  words  used  are  ‘may not’ these  must  be\ninterpreted   as   ‘cannot’   as   it   is   clear   that   the\nintention is to limit  the  time during which an\naward may be challenged.  This interpretation\nis   supported   by   material   relating   to   the\ndiscussions amongst the drafters of the Model\nLaw.  It appears to me that the court would not\nbe   able   to   entertain   any   application   lodged\nafter the expiry of the three months period as\n\nArticle   34\nhas   been   drafted   as   the   all­\nencompassing, and only, basis for challenging\nan award in court.  It does not provide for any\nextension of the time period and, as the court\nderives its jurisdiction to hear the application\nfrom the Article alone, the absence of such a\nprovision   means   the   court   has   not   been\nconferred with the power to extend time\".\n\n(d) The   limitation   provision   in   Section   34(3)   also   provides\n\nfor condonation of delay. Unlike\nSection 5\nof Limitation\n\nAct,   the   delay   can   only   be   condoned   for   30   days   on\n\nshowing   sufficient   cause.   The   crucial   phrase   “but   not\nthereafter”  reveals the legislative intent to  fix  an outer\n\nboundary period for challenging an Award.\n\n(e) Once   the   time   limit   or   extended   time   limit   for\n\nchallenging   the   arbitral   award   expires,   the   period   for\n\nenforcing the award under\nSection 36\nof the Arbitration\n\nAct commences. This is evident from the phrase “where\n\nthe   time   for   making   an   application   to   set   aside   the\n\narbitral award under Section 34 has expired”.2  There is\n\nan integral nexus between the period prescribed under\n\nSection   34(3)   to   challenge   the   Award   and   the\n\ncommencement of the enforcement period under Section\n\n36 to execute the Award.\n\n35. If\nSection   17\nof   the   Limitation   Act   were   to   be   applied   to\n\ndetermining   the   limitation   period   under   Section   34(3),   it\n\nwould have the following consequences\n\n(a) In   Section   34(3),   the   commencement   period   for\n\ncomputing limitation is the date of receipt of award or\n\n2 36. Enforcement.—Where  the time for making an application to set aside\nthe arbitral award under section 34 has expired, or such application having\nbeen made, it has been refused, the award shall be enforced under\nthe Code\nof Civil Procedure\n, 1908 (5 of 1908) in the same manner as if it were a decree\nof the Court.\nthe   date   of   disposal   of   request   under   Section   33   (i.e\n\ncorrection/additional award).\n\nIf\nSection   17\nwere   to   be   applied   for   computing   the\n\nlimitation   period   under   Section   34(3),   the   starting\n\nperiod of limitation would be the date of discovery of\n\nthe   alleged   fraud   or   mistake.   The   starting   point   for\n\nlimitation under Section 34(3) would be different from\n\nthe\nLimitation Act\n.\n\n(b) The   proviso   to   Section   34(3)   enables   a   Court   to\n\nentertain   an   application   to   challenge   an   Award   after\n\nthe three months period is expired, but only within an\n\nadditional period of thirty dates, “but not thereafter”.\n\nThe use of the phrase “but not thereafter” shows that\n\nthe   120   days   period   is   the   outer   boundary   for\n\nchallenging an Award. If\nSection 17\nwere to be applied,\n\nthe outer boundary for challenging an Award could go\n\nbeyond   120   days.   The   phrase   “but   not   thereafter”\n\nwould   be   rendered redundant  and  otiose.  This Court\n\nhas   consistently   taken   this  view   that   the   words   “but\n\nnot thereafter” in the proviso of\nSection 34 (3)\nof the\n\nArbitration   Act   are   of   a   mandatory   nature,   and\ncouched  in negative terms, which leaves no room for\n\ndoubt.   (\nState   of   Himachal   Pradesh   v.   Himachal\n\nTechno   Engineers   &   Anr.\n,   (\n2010)   12   SCC   210,\n\nAssam Urban Water Supply & Sewerage Board v.\n\nSubash   Projects   &   Marketing   Ltd.\n,   (2012)   2   SCC\n\n624 and Anilkumar Jinabhai Patel (D) through\nLRs\n\nv. Pravinchandra Jinabhai Patel & Ors.\n, (2018) SCC\n\nOnline SC 276)\n\n36. In our view, the aforesaid inconsistencies with the language\n\nof\nSection 34(3)\nof Arbitration Act tantamount to an “express\n\nexclusion” of\nSection 17\nof Limitation Act.\n\n37. This Court in\nPopular Construction\nCase  (supra)  at page\n\n474  followed   the   same   approach   when   it   relied   on   the\n\nphrase   “but   not   thereafter”   to   hold   that\nSection   5\nof\n\nLimitation Act was expressly excluded.\n\n12. As far as the language of Section 34 of the\n1996 Act is concerned, the crucial words are “but\nnot thereafter” used in the proviso to sub­section\n(3). In our opinion, this phrase would amount to\nan   express   exclusion   within   the   meaning   of\n\nSection   29(2)\nof   the   Limitation   Act,   and   would\ntherefore bar the application of\nSection 5\nof that\nAct.   Parliament   did   not   need   to   go   further.  To\nhold   that   the   court   could   entertain   an\napplication   to   set   aside   the   award   beyond   the\nextended period under the proviso, would render\nthe phrase “but not thereafter” wholly otiose. No\nprinciple   of   interpretation   would   justify   such   a\nresult.\n\n(emphasis added)\n\n38. Further,   the   exclusion   of\nSection   17\nis   also   necessarily\n\nimplied   when   one   looks   at   the   scheme   and   object   of   the\n\nArbitration Act\n.\n\n39. First,  the   purpose   of\nArbitration   Act\nwas   to   provide   for   a\n\nspeedy dispute resolution process. The Statement of Objects\n\nand   Reasons   reveal   that   the   legislative   intent   of   enacting\n\nthe\nArbitration Act\nwas to provide parties with an efficient\n\nalternative   dispute   resolution   system   which   gives   litigants\n\nan   expedited   resolution   of   disputes   while   reducing   the\n\nburden on the courts.\nArticle 34(3)\nreflects this intent when\n\nit   defines   the   commencement   and   concluding   period   for\n\nchallenging an Award. This Court in\nPopular Construction\n\nCase (supra) highlighted the importance of the fixed periods\n\nunder the\nArbitration Act\n. We may also add that the finality\n\nis a fundamental principle enshrined under the\nArbitration\n\nAct\nand a definitive time limit for challenging an Award is\n\nnecessary   for   ensuring   finality.   If\nSection   17\nwere   to   be\napplied, an Award can be challenged even after 120 days.\n\nThis would defeat the\nArbitration Act\n’s objective of speedy\n\nresolution of disputes. The finality of award would also be in\n\na limbo as a party can challenge an Award even after the\n\n120 day period.\n\n40. Second, extending\nSection 17\nof Limitation Act to Section 34\n\nwould do violence to the scheme of the\nArbitration Act\n. As\n\ndiscussed   above,   Section   36   enables   a   party   to   apply   for\n\nenforcement   of   Award   when   the   period   for   challenging   an\n\nAward under S.34 has expired. However, if\nSection 17\nwere\n\nto be extended to Section 34, the determination of “time for\n\nmaking   an   application   to   set   aside   the   arbitral   award”   in\n\nSection   36   will  become uncertain  and  create  confusion in\n\nthe  enforcement of Award. This runs counter to the scheme\n\nand object of the\nArbitration Act\n.\n\n41. Third, Section 34(3) reflects the principle of unbreakability.\n\nDr.   Peter   Binder   in   International   Commercial   Arbitration\n\nand Conciliation in UNCITRAL Model Law Jurisdictions, 2 nd\n\nEd., observed:\n\n“An application for setting aside an award can\nonly   be   made   during   the   three   months\nfollowing the date on which the party making\nthe application has received the award. Only if\na  party   has   made a request for   correction  or\ninterpretation of the award under\nArt. 33\ndoes\nthe time limit of three months begin after the\ntribunal   has   disposed   of   the   request.   This\nexception from the three­month time limit was\nsubject to criticism in the Working group due\nto   fears   that   it   could   be   used   as   a   delaying\ntactics.   However,   although   “an   unbreakable\ntime   limit   for   applications   for   setting   aside”\nwas sought as being desirable for the sake of\n“certainty and expediency” the prevailing view\nwas that the words ought to be retained “since\nthey presented the reasonable consequence of\narticle   33”.  According  to  this  “unbreakability”\nof   time   limit   and   true   to   the   “certainty   and\nexpediency”   of   the   arbitral   awards,   any\ngrounds   for   setting   aside   the   award   that\nemerge   after   the   three­month   time   limit   has\nexpired cannot be raised.\n\n42. Extending\nSection   17\nof   the   Limitation   Act   would   go\n\ncontrary to the principle of ‘unbreakability’ enshrined under\n\nSection 34(3)\nof the Arbitration Act.\n\n43. The   Respondents   have   argued   that   if\nSection   17\nis   not\n\nextended to Section 34, it would cause enormous injustice\n\nand   provide   scope   for   parties   to   play   mischief.   The\n\nRespondents   have   cited   several   illustrations   where   on\n\naccount   of   fraud   of   the   party,   an   objecting   party   can   be\n\nprecluded from challenging an Award and extending\nSection\nwould come to the rescue of such a party.\n44. The   Respondent’s   contention   proceeds   on   a   misconceived\n\nnotion of\nSection 17\n. Even if\nSection 17\nwere to be extended\n\nto   Section   34,   it   would   not   address   the   Respondent’s\n\ngrievance.\nSection 17\ndoes not defer the starting point of the\n\nlimitation   period   merely   because   the   Appellants   has\n\ncommitted fraud.\nSection 17\ndoes not encompass all kinds\n\nof   frauds   and   mistakes.\nSection   17(1)(b)\nand   (d)   only\n\nencompasses   only   those   fraudulent   conduct   or   act   of\n\nconcealment   of   documents  which   have   the   effect   of\n\nsuppressing   the   knowledge   entitling   a   party   to   pursue   its\n\nlegal remedy. Once a party becomes aware of the antecedent\n\nfacts necessary to pursue a legal proceeding, the limitation\n\nperiod commences.\n\n45. This   principle   is   illustrated   by   a   ruling   of   this   Court   in\n\nYeswant   Deorao   Deshmukh   v.   Walchand   Ramchand\n\nKothari\n, 1950 SCR 852. The facts of this case are broadly\n\nsimilar. A decree holder files an execution petition after the\n\nexpiry   of   limitation   period   (12   years   of   the   passing   of\n\ndecree).   To   overcome  the   limitation  bar,   the   decree­holder\n\nalleged that the judgement debtor prevented the execution\nof a decree by suppressing the ownership of certain assets\n\n(ownership   of   newspaper   in   those   facts)   and   in   support\n\nplaced   reliance   on   Section   18   of   Limitation   Act,   1908\n\n(equivalent   of\nSection   17\n)3  Rejecting   this   contention,   this\n\nCourt observed:\n\n19. In   our   opinion,   the   facts   necessary   to\nestablish   fraud   under\nSection   18\nof   the\nLimitation   Act   are   neither   admitted   nor\nproved in the present case. Concealing from a\nperson the knowledge of his right to apply for\nexecution of a decree is undoubtedly different\nfrom preventing him from exercising his right,\nof which he has knowledge.\nSection 18\nof the\nLimitation   Act   postulates   the   former\nalternative.   ……   The   fraud   pleaded,   namely\nsuppression   of   ownership   of\nthe Prabhat newspaper,  did   not   conceal  from\nhim   his   right   to   make   an   application   for\nexecution of the decree.\n\n46. Similarly  in\nPallav  Sheth v. Custodian\n, (2001) 7 SCC  549,\n\nthis Court observed that\nSection 17\ncomes to the rescue of a\n\nparty for “failing to adopt legal proceedings when the facts or\n\nmaterial   necessary   for   him   to   do   so   have   been   willfully\n\nconcealed from him \"\n\n3 Although there is a slight difference in the text of S.18 of Limitation Act, 1908 and\nS.17\n\nof Limitation Act, 1963, the relevant provision for the present case remains the same.\n47. In the context of Section 34, a party can challenge an award\n\nas soon as it receives the award. Once an award is received,\n\na   party   has   knowledge   of   the   award   and   the   limitation\n\nperiod   commences.   The   objecting   party   is   therefore\n\nprecluded from invoking\nSection 17(1)(b)\n& (d) once it has\n\nknowledge   of   the   Award.\nSection   17(1)(a)\nand   (c)   of\n\nLimitation Act\nmay not even apply, if they are extended to\n\nSection   34,   since   they   deal   with   a   scenario   where   the\n\napplication is “based upon” the fraud of the respondent or if\n\nthe   application   is   for   “relief   from   the   consequences   of   a\n\nmistake”. Section 34 application is based on the award and\n\nnot on the fraud of the respondent and does not seek the\n\nrelief of consequence of a mistake.\n\n48. The fraudulent conduct where\nSection 17\nof the Limitation\n\nAct   would   have   helped   the   objecting   party   is   where   there\n\nwas a fraud in the delivery of the award. However, in such a\n\nscenario,   resort  to\nsection  17\nis not  necessary. If there is\n\nany   fraud   in   the   delivery   of   Award,   the   requirement   of\n\nreceipt of Award under Section 34(3) itself is not satisfied.\n\nAny receipt of Award must be effective receipt. This Court in\nUnion   of   India   v.   Tecco   Trichy   Engineers   &\n\nContractors\n, (2005) 4 SCC 239 held that:\n\n“8.  The delivery of an arbitral award under\nsub­section (5) of\nSection 31\nis not a matter\nof mere formality. It is a matter of substance.\nIt   is   only   after   the   stage   under\nSection   31\n\nhas passed that the stage of termination of\narbitral   proceedings   within   the   meaning   of\n\nSection 32\nof the Act arises.  The delivery of\narbitral   award   to   the   party,   to   be   effective,\nhas   to   be   “received”   by   the   party.  This\ndelivery by the Arbitral Tribunal and receipt\nby   the   party   of   the   award   sets   in   motion\nseveral   periods   of   limitation   such   as   an\napplication for correction and interpretation\nof   an   award   within   30   days   under   Section\n33(1),   an   application   for   making   an\nadditional award under Section 33(4) and an\napplication for setting aside an award under\nSection 34(3) and so on. As this delivery of\nthe copy of award has the effect of conferring\ncertain rights on the party as also bringing to\nan end the right to exercise those rights on\nexpiry  of  the  prescribed period of limitation\nwhich   would   be   calculated   from   that   date,\nthe   delivery   of   the   copy   of   award   by   the\nTribunal   and   the   receipt   thereof   by   each\nparty   constitutes an important stage in the\narbitral proceedings.\n\n9. In the context of a huge organisation like\nthe Railways, the copy of the award has to\nbe   received   by   the   person   who   has\nknowledge   of   the   proceedings   and   who\nwould be the best person to understand and\nappreciate   the   arbitral   award   and   also   to\ntake a decision in the matter of moving an\napplication   under   sub­section   (1)   or   (5)   of\nSection   33   or   under   sub­section   (1)   of\nSection 34”.\n\n49. In   view   of   the   above,   we   hold   that   once   the   party   has\n\nreceived   the   Award,   the   limitation   period   under\nSection\n\n34(3)\nof the  Arbitration Act commences.\nSection 17\nof the\n\nLimitation   Act   would   not   come   to   the   rescue   of   such\n\nobjecting party.\n\n50. In   the   present   case,   the   Respondents   had   a   right   to\n\nchallenge   the   Award   under   Section   34   the   moment   they\n\nreceived it. In this case, Respondents received the Award on\n\n21.02.2010. The alleged MoU was executed on  09.04.2010.\n\nOnce the Respondents received the Award, the time under\n\nSection   34(3)   commenced   and   any   subsequent   disability\n\neven   as   per\nSection   17\nor\nSection   9\nof   Limitation   Act   is\n\nimmaterial.   Merely   because   the   Appellant   had   committed\n\nsome   fraud,   it   would   not   affect   the   Respondents   right   to\n\nchallenge   the   Award   if   the   facts   entitling   the   filing   of   a\n\nSection   34   Application   was   within   their   knowledge.     The\n\nmoment   the   Respondents   have   received   the   Award,   the\n\nthree months period prescribed under Section 34(3) begins\n\nto   commence.     It   was   incumbent   on   the   Respondents   to\nhave instituted an application under Section 34 challenging\n\nan award.  Therefore, in light of the discussion above, there\n\nwould  not have  been any point for meaningful remand as\n\nthe   question   of   law   is   answered   against   the   Respondents\n\nherein.\n\n51. In   light   of   the   aforesaid   legal   position,   the   judgment   and\n\norder of the High court dated 18.06.2012, in Civil Revision\n\nPetition Nos. 2151, 2246, 2383 and 2458 of 2012 are set­\n\naside,   and   also   the   order   allowing   I.A.   No.   598   of   2011\n\ncondoning the delay of 236 days in filing the objections is\n\nset   aside,   accordingly   these   appeals   are   allowed   with   no\n\norder as to costs.\n\n………………………J.\n(N. V. Ramana)\n\n………………………J.\n(S. Abdul Nazeer)\nNew Delhi,\nSeptember 26, 2018",
  "metadata": {
    "processed_date": "2026-01-18T18:40:36.903821",
    "version": "2.0",
    "court": "Supreme Court Of India",
    "court_level": "SC",
    "case_number": "UNKNOWN",
    "decision_date": "26 SEPTEMBER, 2018",
    "jurisdiction": "India",
    "bench": "S. ABDUL NAZEER , N. V. RAMANA  REPORTABLE  IN THE SUPREME COURT OF INDIA CIVIL APPELLATE JURISDICTION  CIVIL APPEAL NO(S). 7710­7713 OF 2013  P. RADHA BAI AND ORS. …APPELLANT(S)  VERSUS P. ASHOK KUMAR AND ANR.               …RESPONDENT(S)  J U D G M E N T N.V. RAMANA, J.  1. THESE   APPEALS   ARE   FILED,   AGGRIEVED   BY   THE   JUDGMENT   AND  ORDER DATED  18.06.2012 IN THE CIVIL REVISION PETITION NOS.  2151,   2246,   2383   AND   2458   OF   2012   PASSED   BY   THE   HIGH  COURT OF JUDICATURE AT ANDHRA PRADESH AT HYDERABAD.  2. AN   INTERESTING   QUESTION   OF   LAW   ARISES   IN   THIS   BATCH   OF  PETITIONS, CONCERNING THE APPLICABILITY OF SECTION 17 OF THE  LIMITATION ACT, 1963 [‘ LIMITATION ACT ’] FOR CONDONATION OF A  DELAY CAUSED ON THE ACCOUNT OF ALLEGED FRAUD PLAYED ON THE  SIGNATURE NOT VERIFIED  DIGITALLY SIGNED BY  VISHAL ANAND  DATE: 2018.09.26  14:57:29 IST  OBJECTOR   (PARTY   CHALLENGING   THE   AWARD)   BEYOND   THE   PERIOD  REASON: PRESCRIBED   UNDER SECTION   34   (3) OF   THE   ARBITRATION   AND  CONCILIATION ACT OF 1996 [‘ ARBITRATION ACT ’].  3. THE FACTS WHICH GIVE RISE TO THIS QUESTION FALL INTO A NARROW  COMPASS.   ORIGINALLY   ONE   MR.   P.   KISHAN   LAL   CARRIED   ON  BUSINESS   AND   ACQUIRED   SEVERAL   PROPERTIES.     ON   HIS   DEATH,  MR.   P.   KISHAN   LAL   WAS   SURVIVED   BY   EIGHT   (8)   LEGAL   HEIRS  (APPELLANT NOS. 1 TO 6 AND RESPONDENT NOS. 1 AND 2).  4. AFTER   THE   DEATH   OF   MR.   KISHAN   LAL,   SEVERAL   DISPUTES   HAVE  CROPPED UP ON THE DIVISION OF PROPERTIES.   HAVING FAILED TO  RESOLVE THE DISPUTE, THE PARTIES TURNED TOWARDS ARBITRATION  TO RESOLVE THE DISPUTE.   FIVE ARBITRATORS WERE APPOINTED TO  ADJUDICATE   AND   DISTRIBUTE   ELEVEN   PROPERTIES   BELONGING   TO  THEM.  5. ON 18.02.2010, THE ARBITRATORS PASSED A UNANIMOUS AWARD  PROVIDING FOR THE DIVISION OF PROPERTIES AND BUSINESSES. THE  PARTIES   RECEIVED   THE   AWARD   ON   21.02.2010.     THERE   IS   NO  DISPUTE ON THE RECEIPT OF THE AWARD BY THE PARTIES."
  },
  "extractions": {
    "citations": {
      "total": 9,
      "by_type": {
        "reporter": 2,
        "case_name": 7
      },
      "details": [
        {
          "type": "reporter",
          "reporter": "AIR",
          "year": "1964",
          "page": "1099",
          "raw": "AIR   1964   SC   1099",
          "start_pos": 18753,
          "end_pos": 18775,
          "court": "SC",
          "is_landmark": false
        },
        {
          "type": "reporter",
          "reporter": "SCC",
          "year": "2019",
          "page": "445",
          "raw": "2019 (13) SCC 445",
          "start_pos": 127,
          "end_pos": 144,
          "is_landmark": false
        },
        {
          "type": "case_name",
          "petitioner": "Vidyacharan Shukla",
          "respondent": "Khubchand Baghel",
          "case_name": "Vidyacharan Shukla v. Khubchand Baghel",
          "raw": "in\nVidyacharan   Shukla   v.\n\nKhubchand Baghel\n,",
          "start_pos": 15631,
          "end_pos": 15679,
          "is_landmark": false
        },
        {
          "type": "case_name",
          "petitioner": "Hukumdev Narain Yadav",
          "respondent": "Lalit Narain Mishra",
          "case_name": "Hukumdev Narain Yadav v. Lalit Narain Mishra",
          "raw": "in\nHukumdev\n\nNarain Yadav v. Lalit Narain Mishra\n,",
          "start_pos": 19589,
          "end_pos": 19639,
          "is_landmark": false
        },
        {
          "type": "case_name",
          "petitioner": "Commissioner of Customs and Central Excise",
          "respondent": "Hongo India",
          "case_name": "Commissioner of Customs and Central Excise v. Hongo India",
          "raw": "in\nCommissioner of Customs\n\nand Central Excise v. Hongo India (",
          "start_pos": 21056,
          "end_pos": 21119,
          "is_landmark": false
        },
        {
          "type": "case_name",
          "petitioner": "Union of India",
          "respondent": "Popular Construction Co.",
          "case_name": "Union of India v. Popular Construction Co.",
          "raw": "in\nUnion of\n\nIndia v. Popular Construction Co.\n,",
          "start_pos": 22763,
          "end_pos": 22811,
          "is_landmark": false
        },
        {
          "type": "case_name",
          "petitioner": "Yeswant Deorao Deshmukh",
          "respondent": "Walchand Ramchand Kothari",
          "case_name": "Yeswant Deorao Deshmukh v. Walchand Ramchand Kothari",
          "raw": "in\n\nYeswant   Deorao   Deshmukh   v.   Walchand   Ramchand\n\nKothari\n,",
          "start_pos": 37420,
          "end_pos": 37489,
          "is_landmark": false
        },
        {
          "type": "case_name",
          "petitioner": "Pallav Sheth",
          "respondent": "Custodian",
          "case_name": "Pallav Sheth v. Custodian",
          "raw": "in\nPallav  Sheth v. Custodian\n,",
          "start_pos": 38764,
          "end_pos": 38795,
          "is_landmark": false
        },
        {
          "type": "case_name",
          "petitioner": "Union of India",
          "respondent": "Tecco Trichy Engineers & Contractors",
          "case_name": "Union of India v. Tecco Trichy Engineers & Contractors",
          "raw": "in\nUnion   of   India   v.   Tecco   Trichy   Engineers   &\n\nContractors\n,",
          "start_pos": 40503,
          "end_pos": 40577,
          "is_landmark": false
        }
      ]
    },
    "sections": {
      "total": 0,
      "by_act": {},
      "details": []
    },
    "transitions": {
      "total": 0,
      "by_source": {},
      "details": []
    },
    "landmarks": {
      "total": 0,
      "by_id": {},
      "details": []
    },
    "issues": {
      "total": 3,
      "details": {
        "arbitration": {
          "statute": "Arbitration Act",
          "keywords": [
            "arbitration"
          ],
          "sections": [
            "34",
            "36"
          ],
          "confidence": "high",
          "keyword_count": 1,
          "mention_count": 46
        },
        "jurisdiction": {
          "statute": "CPC",
          "keywords": [
            "jurisdiction"
          ],
          "sections": [
            "9"
          ],
          "confidence": "high",
          "keyword_count": 1,
          "mention_count": 3
        },
        "limitation": {
          "statute": "Limitation Act",
          "keywords": [
            "limitation",
            "delay",
            "condonation"
          ],
          "sections": [
            "3",
            "5"
          ],
          "confidence": "high",
          "keyword_count": 3,
          "mention_count": 117
        }
      }
    }
  },
  "provenance": {
    "processed_date": "2026-01-18T18:40:36.903821",
    "pipeline_version": "2.0",
    "processing_steps": [
      "ingestion",
      "metadata_extraction",
      "issue_extraction",
      "classification",
      "statutory_transitions",
      "citation_extraction",
      "consolidation"
    ]
  },
  "classification": {
    "domain": "civil",
    "confidence": "high",
    "signals": {
      "criminal": [],
      "civil": [
        "Limitation Act",
        "arbitration",
        "defendant",
        "plaintiff",
        "decree",
        "Arbitration",
        "suit"
      ],
      "service": []
    }
  }
}